
{
  "version": "7.0.1",
  "date": "2025-06-29",
  "notes": [
    {
      "type": "fix",
      "title": "Correção de Notificações",
      "desc": "A seção de configuração de alertas foi restaurada e agora funciona corretamente."
    },
    {
      "type": "fix",
      "title": "Sistema de Update",
      "desc": "Resolvido problema que impedia a visualização das notas de atualização se o app já estivesse na versão mais recente."
    },
    {
      "type": "ui",
      "title": "Notas de Versão",
      "desc": "Agora é possível visualizar este changelog a qualquer momento através do menu de Ajustes."
    }
  ]
}
